xgrep/__init__.py
xgrep/cell.py
xgrep/cli.py
xgrep/col.py
xgrep/excel.py
xgrep/grid.py
xgrep/match.py
xgrep/row.py
xgrep-0.2.12.dist-info/METADATA
xgrep-0.2.12.dist-info/WHEEL
xgrep-0.2.12.dist-info/entry_points.txt
xgrep-0.2.12.dist-info/licenses/LICENSE
xgrep-0.2.12.dist-info/RECORD
