Metadata-Version: 2.4
Name: xgrep
Version: 0.2.12
Summary: xgrep: A grep for Excel (and CSV/TSV) files.
Project-URL: Homepage, https://github.com/terrycojones/xgrep
Project-URL: Issues, https://github.com/terrycojones/xgrep/issues
Author-email: terrycojones <tcj25@cam.ac.uk>
License-File: LICENSE
Classifier: License :: OSI Approved :: MIT License
Classifier: Operating System :: OS Independent
Classifier: Programming Language :: Python :: 3
Requires-Python: >=3.10
Requires-Dist: click-option-group>=0.5.9
Requires-Dist: click>=8.3.1
Requires-Dist: fastexcel>=0.18.0
Requires-Dist: openpyxl>=3.1.5
Requires-Dist: polars>=1.37.1
Requires-Dist: rich>=14.2.0
Requires-Dist: xlsx2csv>=0.8.4
Requires-Dist: xlsxwriter>=3.2.9
